README.md
setup.cfg
setup.py
prompt_tr/__init__.py
prompt_tr/__main__.py
prompt_tr/prompt_tr.py
prompt_tr_free.egg-info/PKG-INFO
prompt_tr_free.egg-info/SOURCES.txt
prompt_tr_free.egg-info/dependency_links.txt
prompt_tr_free.egg-info/requires.txt
prompt_tr_free.egg-info/top_level.txt